sdss/__init__.py
sdss/objects.py
sdss/photometry.py
sdss/refs.py
sdss/regions.py
sdss/utils.py
sdss-1.1.1.dist-info/LICENSE.txt
sdss-1.1.1.dist-info/METADATA
sdss-1.1.1.dist-info/WHEEL
sdss-1.1.1.dist-info/top_level.txt
sdss-1.1.1.dist-info/RECORD
