Metadata-Version: 2.1
Name: sdss
Version: 1.1.1
Summary: A python package for retrieving and analysing data from SDSS (Sloan Digital Sky Survey)
Home-page: https://github.com/behrouzz/sdss
Author: Behrouz Safari
Author-email: behrouz.safari@gmail.com
License: MIT
Classifier: Programming Language :: Python :: 3
Classifier: License :: OSI Approved :: MIT License
Classifier: Operating System :: OS Independent
Requires-Python: >=3.8
License-File: LICENSE.txt
Requires-Dist: numpy
Requires-Dist: requests
Requires-Dist: Pillow
Requires-Dist: matplotlib
Requires-Dist: pandas
Requires-Dist: astropy
